LICENSE
MANIFEST.in
README.rst
VERSION
jobs.py
pyproject.toml
setup.py
jobspy.egg-info/PKG-INFO
jobspy.egg-info/SOURCES.txt
jobspy.egg-info/dependency_links.txt
jobspy.egg-info/requires.txt
jobspy.egg-info/top_level.txt