Metadata-Version: 2.4
Name: jobspy
Version: 0.30.1
Summary: Use Redis as a job input/output coordinator.
Home-page: https://github.com/josiahcarlson/jobs
Author: Josiah Carlson
Author-email: Josiah Carlson <josiah.carlson@gmail.com>
Maintainer-email: Josiah Carlson <josiah.carlson@gmail.com>
Project-URL: Repository, https://github.com/josiahcarlson/jobs/
Project-URL: Changelog, https://github.com/josiahcarlson/jobs/blob/master/changelog.txt
Classifier: Development Status :: 5 - Production/Stable
Classifier: License :: OSI Approved :: GNU Library or Lesser General Public License (LGPL)
Classifier: Programming Language :: Python
Classifier: Topic :: Software Development :: Libraries :: Python Modules
Classifier: Programming Language :: Python
Classifier: Programming Language :: Python :: 2.7
Classifier: Programming Language :: Python :: 3.5
Classifier: Programming Language :: Python :: 3.6
Classifier: Programming Language :: Python :: 3.7
Classifier: Programming Language :: Python :: 3.8
Classifier: Programming Language :: Python :: 3.9
Classifier: Programming Language :: Python :: 3.10
Classifier: Programming Language :: Python :: 3.11
Classifier: Development Status :: 4 - Beta
Classifier: Programming Language :: Python
License-File: LICENSE
Requires-Dist: redis>=3.0.0
Dynamic: author
Dynamic: home-page
Dynamic: license-file
